kubeinfra_python/__init__.py
kubeinfra_python-0.1.0.dist-info/METADATA
kubeinfra_python-0.1.0.dist-info/WHEEL
kubeinfra_python-0.1.0.dist-info/RECORD
