Metadata-Version: 2.1
Name: kubeinfra-python
Version: 0.1.0
Summary: 
Author: liuf
Author-email: liuf@kubesphere.io
Requires-Python: >=3.12,<4.0
Classifier: Programming Language :: Python :: 3
Classifier: Programming Language :: Python :: 3.12
Requires-Dist: requests (>=2.31.0,<3.0.0)
